api_driver/__init__.py
api_driver/__main__.py
api_driver/_version.py
api_driver/ad_utils.py
api_driver/adf.py
api_driver/adf_proxy.py
api_driver/capture2testcase.py
api_driver/command.py
api_driver/har_parser.py
api_driver/loader_swagger.py
api_driver/project_generator.py
api_driver/swagger_generate.py
api_driver/template.py
api_driver/testcase_mixin.py
api_driver/templates/api.tpl
api_driver/templates/api_demo.tpl
api_driver/templates/base_testcase.tpl
api_driver/templates/har2api_case.tpl
api_driver/templates/har2case.tpl
api_driver/templates/http.tpl
api_driver/templates/report_template.html
api_driver/templates/testcase_demo.tpl
api_driver/utils/__init__.py
api_driver/utils/custom_str_utils.py
api_driver/utils/database_conn.py
api_driver/utils/fake.py
api_driver/utils/placeholder.py
api_driver/utils/service_logger.py
apidriver-0.9.5.dist-info/LICENSE.txt
apidriver-0.9.5.dist-info/METADATA
apidriver-0.9.5.dist-info/WHEEL
apidriver-0.9.5.dist-info/entry_points.txt
apidriver-0.9.5.dist-info/top_level.txt
apidriver-0.9.5.dist-info/RECORD
