Metadata-Version: 2.1
Name: apidriver
Version: 0.9.5
Summary: api test framework cli
Home-page: https://github.com/CHNJX/api-driver
Author: CHNJX
Author-email: chaozhourose@gmail.com
License: UNKNOWN
Platform: UNKNOWN
Requires-Dist: allure-pytest ==2.12.0
Requires-Dist: allure-python-commons ==2.12.0
Requires-Dist: asgiref ==3.5.2
Requires-Dist: attrs ==22.2.0
Requires-Dist: bleach ==6.0.0
Requires-Dist: Brotli ==1.0.9
Requires-Dist: certifi ==2022.12.7
Requires-Dist: cffi ==1.15.1
Requires-Dist: charset-normalizer ==3.0.1
Requires-Dist: click ==8.1.3
Requires-Dist: colorama ==0.4.6
Requires-Dist: cryptography ==38.0.4
Requires-Dist: docutils ==0.19
Requires-Dist: exceptiongroup ==1.1.0
Requires-Dist: execnet ==2.0.2
Requires-Dist: Faker ==16.6.1
Requires-Dist: Flask ==2.2.5
Requires-Dist: h11 ==0.14.0
Requires-Dist: h2 ==4.1.0
Requires-Dist: hpack ==4.0.0
Requires-Dist: hyperframe ==6.0.1
Requires-Dist: idna ==3.4
Requires-Dist: importlib-metadata ==6.0.0
Requires-Dist: iniconfig ==2.0.0
Requires-Dist: itsdangerous ==2.1.2
Requires-Dist: jaraco.classes ==3.2.3
Requires-Dist: Jinja2 ==3.1.2
Requires-Dist: jsonpath ==0.82
Requires-Dist: jsonschema ==4.17.3
Requires-Dist: kaitaistruct ==0.10
Requires-Dist: keyring ==23.13.1
Requires-Dist: ldap3 ==2.9.1
Requires-Dist: markdown-it-py ==2.1.0
Requires-Dist: MarkupSafe ==2.1.2
Requires-Dist: mdurl ==0.1.2
Requires-Dist: mitmproxy ==9.0.1
Requires-Dist: mitmproxy-wireguard ==0.1.23
Requires-Dist: more-itertools ==9.0.0
Requires-Dist: msgpack ==1.0.5
Requires-Dist: packaging ==23.0
Requires-Dist: passlib ==1.7.4
Requires-Dist: pkginfo ==1.9.6
Requires-Dist: pluggy ==1.0.0
Requires-Dist: protobuf ==4.24.1
Requires-Dist: publicsuffix2 ==2.20191221
Requires-Dist: pyasn1 ==0.5.0
Requires-Dist: pycparser ==2.21
Requires-Dist: Pygments ==2.14.0
Requires-Dist: PyHamcrest ==2.0.4
Requires-Dist: PyMySQL ==1.0.2
Requires-Dist: pyOpenSSL ==22.1.0
Requires-Dist: pyparsing ==3.0.9
Requires-Dist: pyperclip ==1.8.2
Requires-Dist: pyrsistent ==0.19.3
Requires-Dist: pytest ==7.2.1
Requires-Dist: pytest-xdist ==3.3.1
Requires-Dist: python-dateutil ==2.8.2
Requires-Dist: pywin32-ctypes ==0.2.0
Requires-Dist: PyYAML ==6.0
Requires-Dist: readme-renderer ==37.3
Requires-Dist: requests ==2.28.2
Requires-Dist: requests-toolbelt ==0.10.1
Requires-Dist: rfc3986 ==2.0.0
Requires-Dist: rich ==13.3.1
Requires-Dist: ruamel.yaml ==0.17.32
Requires-Dist: ruamel.yaml.clib ==0.2.7
Requires-Dist: six ==1.16.0
Requires-Dist: sortedcontainers ==2.4.0
Requires-Dist: tomli ==2.0.1
Requires-Dist: tornado ==6.3.3
Requires-Dist: twine ==4.0.2
Requires-Dist: typing-extensions ==4.4.0
Requires-Dist: urllib3 ==1.26.14
Requires-Dist: urwid ==2.1.2
Requires-Dist: webencodings ==0.5.1
Requires-Dist: Werkzeug ==2.3.7
Requires-Dist: wsproto ==1.2.0
Requires-Dist: zipp ==3.12.1
Requires-Dist: zstandard ==0.19.0
